unichat_mcp_server/__init__.py
unichat_mcp_server/server.py
unichat_mcp_server-0.2.19.dist-info/METADATA
unichat_mcp_server-0.2.19.dist-info/WHEEL
unichat_mcp_server-0.2.19.dist-info/entry_points.txt
unichat_mcp_server-0.2.19.dist-info/licenses/LICENSE
unichat_mcp_server-0.2.19.dist-info/RECORD
