Metadata-Version: 2.4
Name: unichat-mcp-server
Version: 0.2.19
Summary: Unichat MCP Server
Author-email: Stefan <shear.0-corned@icloud.com>
License-File: LICENSE
Requires-Python: >=3.11
Requires-Dist: mcp>=1.0.0
Requires-Dist: unichat~=3.6.0
